{
  "version": "5",
  "dialect": "mysql",
  "id": "a2ca89b4-b90f-4420-a6c2-c0d6228d40b5",
  "prevId": "f763f364-df18-4d6a-9f7c-ab6becbceb55",
  "tables": {
    "aktivnosti": {
      "name": "aktivnosti",
      "columns": {
        "id": {
          "name": "id",
          "type": "varchar(36)",
          "primaryKey": false,
          "notNull": true,
          "autoincrement": false,
          "default": "(UUID())"
        },
        "naziv": {
          "name": "naziv",
          "type": "varchar(255)",
          "primaryKey": false,
          "notNull": true,
          "autoincrement": false
        },
        "opis": {
          "name": "opis",
          "type": "varchar(512)",
          "primaryKey": false,
          "notNull": false,
          "autoincrement": false
        },
        "tip": {
          "name": "tip",
          "type": "varchar(100)",
          "primaryKey": false,
          "notNull": false,
          "autoincrement": false
        },
        "datum": {
          "name": "datum",
          "type": "timestamp",
          "primaryKey": false,
          "notNull": false,
          "autoincrement": false
        },
        "uradjen": {
          "name": "uradjen",
          "type": "boolean",
          "primaryKey": false,
          "notNull": false,
          "autoincrement": false,
          "default": false
        }
      },
      "indexes": {},
      "foreignKeys": {},
      "compositePrimaryKeys": {
        "aktivnosti_id": {
          "name": "aktivnosti_id",
          "columns": [
            "id"
          ]
        }
      },
      "uniqueConstraints": {},
      "checkConstraint": {}
    },
    "dnevnici": {
      "name": "dnevnici",
      "columns": {
        "id": {
          "name": "id",
          "type": "varchar(36)",
          "primaryKey": false,
          "notNull": true,
          "autoincrement": false,
          "default": "(UUID())"
        },
        "datum": {
          "name": "datum",
          "type": "timestamp",
          "primaryKey": false,
          "notNull": false,
          "autoincrement": false,
          "default": "(now())"
        },
        "vreme": {
          "name": "vreme",
          "type": "varchar(50)",
          "primaryKey": false,
          "notNull": false,
          "autoincrement": false
        },
        "slika": {
          "name": "slika",
          "type": "varchar(512)",
          "primaryKey": false,
          "notNull": false,
          "autoincrement": false
        },
        "kolicina_meda": {
          "name": "kolicina_meda",
          "type": "decimal(10,2)",
          "primaryKey": false,
          "notNull": false,
          "autoincrement": false
        },
        "pregled": {
          "name": "pregled",
          "type": "varchar(512)",
          "primaryKey": false,
          "notNull": false,
          "autoincrement": false
        },
        "komentar": {
          "name": "komentar",
          "type": "varchar(512)",
          "primaryKey": false,
          "notNull": false,
          "autoincrement": false
        },
        "kosnica_id": {
          "name": "kosnica_id",
          "type": "varchar(36)",
          "primaryKey": false,
          "notNull": true,
          "autoincrement": false
        }
      },
      "indexes": {},
      "foreignKeys": {
        "dnevnici_kosnica_id_kosnice_id_fk": {
          "name": "dnevnici_kosnica_id_kosnice_id_fk",
          "tableFrom": "dnevnici",
          "tableTo": "kosnice",
          "columnsFrom": [
            "kosnica_id"
          ],
          "columnsTo": [
            "id"
          ],
          "onDelete": "no action",
          "onUpdate": "no action"
        }
      },
      "compositePrimaryKeys": {
        "dnevnici_id": {
          "name": "dnevnici_id",
          "columns": [
            "id"
          ]
        }
      },
      "uniqueConstraints": {},
      "checkConstraint": {}
    },
    "izvestaji": {
      "name": "izvestaji",
      "columns": {
        "id": {
          "name": "id",
          "type": "varchar(36)",
          "primaryKey": false,
          "notNull": true,
          "autoincrement": false,
          "default": "(UUID())"
        },
        "datum_od": {
          "name": "datum_od",
          "type": "timestamp",
          "primaryKey": false,
          "notNull": true,
          "autoincrement": false
        },
        "datum_do": {
          "name": "datum_do",
          "type": "timestamp",
          "primaryKey": false,
          "notNull": true,
          "autoincrement": false
        },
        "korisnik_id": {
          "name": "korisnik_id",
          "type": "varchar(36)",
          "primaryKey": false,
          "notNull": false,
          "autoincrement": false
        },
        "pcelinjak_id": {
          "name": "pcelinjak_id",
          "type": "varchar(36)",
          "primaryKey": false,
          "notNull": false,
          "autoincrement": false
        }
      },
      "indexes": {},
      "foreignKeys": {
        "izvestaji_korisnik_id_users_id_fk": {
          "name": "izvestaji_korisnik_id_users_id_fk",
          "tableFrom": "izvestaji",
          "tableTo": "users",
          "columnsFrom": [
            "korisnik_id"
          ],
          "columnsTo": [
            "id"
          ],
          "onDelete": "no action",
          "onUpdate": "no action"
        },
        "izvestaji_pcelinjak_id_pcelinjaci_id_fk": {
          "name": "izvestaji_pcelinjak_id_pcelinjaci_id_fk",
          "tableFrom": "izvestaji",
          "tableTo": "pcelinjaci",
          "columnsFrom": [
            "pcelinjak_id"
          ],
          "columnsTo": [
            "id"
          ],
          "onDelete": "no action",
          "onUpdate": "no action"
        }
      },
      "compositePrimaryKeys": {
        "izvestaji_id": {
          "name": "izvestaji_id",
          "columns": [
            "id"
          ]
        }
      },
      "uniqueConstraints": {},
      "checkConstraint": {}
    },
    "kosnice": {
      "name": "kosnice",
      "columns": {
        "id": {
          "name": "id",
          "type": "varchar(36)",
          "primaryKey": false,
          "notNull": true,
          "autoincrement": false,
          "default": "(UUID())"
        },
        "broj": {
          "name": "broj",
          "type": "int",
          "primaryKey": false,
          "notNull": true,
          "autoincrement": false
        },
        "tip": {
          "name": "tip",
          "type": "varchar(100)",
          "primaryKey": false,
          "notNull": false,
          "autoincrement": false
        },
        "datum": {
          "name": "datum",
          "type": "timestamp",
          "primaryKey": false,
          "notNull": false,
          "autoincrement": false,
          "default": "(now())"
        },
        "starost_matice": {
          "name": "starost_matice",
          "type": "int",
          "primaryKey": false,
          "notNull": false,
          "autoincrement": false
        },
        "br_nastavaka": {
          "name": "br_nastavaka",
          "type": "int",
          "primaryKey": false,
          "notNull": false,
          "autoincrement": false
        },
        "pcelinjak_id": {
          "name": "pcelinjak_id",
          "type": "varchar(36)",
          "primaryKey": false,
          "notNull": true,
          "autoincrement": false
        }
      },
      "indexes": {},
      "foreignKeys": {
        "kosnice_pcelinjak_id_pcelinjaci_id_fk": {
          "name": "kosnice_pcelinjak_id_pcelinjaci_id_fk",
          "tableFrom": "kosnice",
          "tableTo": "pcelinjaci",
          "columnsFrom": [
            "pcelinjak_id"
          ],
          "columnsTo": [
            "id"
          ],
          "onDelete": "no action",
          "onUpdate": "no action"
        }
      },
      "compositePrimaryKeys": {
        "kosnice_id": {
          "name": "kosnice_id",
          "columns": [
            "id"
          ]
        }
      },
      "uniqueConstraints": {},
      "checkConstraint": {}
    },
    "notifikacije": {
      "name": "notifikacije",
      "columns": {
        "id": {
          "name": "id",
          "type": "varchar(36)",
          "primaryKey": false,
          "notNull": true,
          "autoincrement": false,
          "default": "(UUID())"
        },
        "korisnik_id": {
          "name": "korisnik_id",
          "type": "varchar(36)",
          "primaryKey": false,
          "notNull": true,
          "autoincrement": false
        },
        "aktivnost_id": {
          "name": "aktivnost_id",
          "type": "varchar(36)",
          "primaryKey": false,
          "notNull": true,
          "autoincrement": false
        }
      },
      "indexes": {},
      "foreignKeys": {
        "notifikacije_korisnik_id_users_id_fk": {
          "name": "notifikacije_korisnik_id_users_id_fk",
          "tableFrom": "notifikacije",
          "tableTo": "users",
          "columnsFrom": [
            "korisnik_id"
          ],
          "columnsTo": [
            "id"
          ],
          "onDelete": "no action",
          "onUpdate": "no action"
        },
        "notifikacije_aktivnost_id_aktivnosti_id_fk": {
          "name": "notifikacije_aktivnost_id_aktivnosti_id_fk",
          "tableFrom": "notifikacije",
          "tableTo": "aktivnosti",
          "columnsFrom": [
            "aktivnost_id"
          ],
          "columnsTo": [
            "id"
          ],
          "onDelete": "no action",
          "onUpdate": "no action"
        }
      },
      "compositePrimaryKeys": {
        "notifikacije_id": {
          "name": "notifikacije_id",
          "columns": [
            "id"
          ]
        }
      },
      "uniqueConstraints": {},
      "checkConstraint": {}
    },
    "pcelinjaci": {
      "name": "pcelinjaci",
      "columns": {
        "id": {
          "name": "id",
          "type": "varchar(36)",
          "primaryKey": false,
          "notNull": true,
          "autoincrement": false,
          "default": "(UUID())"
        },
        "naziv": {
          "name": "naziv",
          "type": "varchar(255)",
          "primaryKey": false,
          "notNull": true,
          "autoincrement": false
        },
        "adresa": {
          "name": "adresa",
          "type": "varchar(255)",
          "primaryKey": false,
          "notNull": false,
          "autoincrement": false
        },
        "geo_sirina": {
          "name": "geo_sirina",
          "type": "decimal(10,8)",
          "primaryKey": false,
          "notNull": false,
          "autoincrement": false
        },
        "geo_duzina": {
          "name": "geo_duzina",
          "type": "decimal(11,8)",
          "primaryKey": false,
          "notNull": false,
          "autoincrement": false
        }
      },
      "indexes": {},
      "foreignKeys": {},
      "compositePrimaryKeys": {
        "pcelinjaci_id": {
          "name": "pcelinjaci_id",
          "columns": [
            "id"
          ]
        }
      },
      "uniqueConstraints": {},
      "checkConstraint": {}
    },
    "users": {
      "name": "users",
      "columns": {
        "id": {
          "name": "id",
          "type": "varchar(36)",
          "primaryKey": false,
          "notNull": true,
          "autoincrement": false,
          "default": "(UUID())"
        },
        "ime": {
          "name": "ime",
          "type": "varchar(100)",
          "primaryKey": false,
          "notNull": true,
          "autoincrement": false
        },
        "prezime": {
          "name": "prezime",
          "type": "varchar(100)",
          "primaryKey": false,
          "notNull": true,
          "autoincrement": false
        },
        "email": {
          "name": "email",
          "type": "varchar(255)",
          "primaryKey": false,
          "notNull": true,
          "autoincrement": false
        },
        "sifra": {
          "name": "sifra",
          "type": "varchar(255)",
          "primaryKey": false,
          "notNull": true,
          "autoincrement": false
        },
        "uloga": {
          "name": "uloga",
          "type": "enum('administrator','pcelar','poljoprivrednik')",
          "primaryKey": false,
          "notNull": true,
          "autoincrement": false
        },
        "created_at": {
          "name": "created_at",
          "type": "timestamp",
          "primaryKey": false,
          "notNull": false,
          "autoincrement": false,
          "default": "(now())"
        }
      },
      "indexes": {},
      "foreignKeys": {},
      "compositePrimaryKeys": {
        "users_id": {
          "name": "users_id",
          "columns": [
            "id"
          ]
        }
      },
      "uniqueConstraints": {
        "users_email_unique": {
          "name": "users_email_unique",
          "columns": [
            "email"
          ]
        }
      },
      "checkConstraint": {}
    }
  },
  "views": {},
  "_meta": {
    "schemas": {},
    "tables": {},
    "columns": {}
  },
  "internal": {
    "tables": {},
    "indexes": {}
  }
}